{"chunk_definitions":[{"chunk_id":"csetup_chunk","chunk_label":"Setup","document_id":"8A819797","expansion_state":0,"options":{"engine":"r","include":"F","label":"Setup"},"row":58,"row_count":1,"visible":true},{"chunk_id":"c3qnwdc8fmer9","chunk_label":"unnamed-chunk-1","document_id":"8A819797","expansion_state":0,"options":{"engine":"R","include":"F","label":"unnamed-chunk-2"},"row":180,"row_count":1,"visible":true},{"chunk_id":"cwqsm1kmwqnwb","chunk_label":"unnamed-chunk-2","document_id":"8A819797","expansion_state":0,"options":{"dev":"svg","echo":"F","engine":"R","fig.fullwidth":"T","label":"unnamed-chunk-3"},"row":194,"row_count":1,"visible":true},{"chunk_id":"ce1xuf178h6ww","chunk_label":"unnamed-chunk-4","document_id":"8A819797","expansion_state":0,"options":{"dev":"svg","echo":"F","engine":"R","fig.fullwidth":"T","label":"unnamed-chunk-1"},"row":234,"row_count":1,"visible":true},{"chunk_id":"ccm1a066nxp8r","chunk_label":"unnamed-chunk-8","document_id":"8A819797","expansion_state":0,"options":{"dev":"svg","echo":"F","engine":"R","fig.fullwidth":"T","label":"unnamed-chunk-5"},"row":292,"row_count":1,"visible":true}],"doc_write_time":1570486753}